CHANGES.rst
CONTRIBUTORS.rst
DEVELOP.rst
LICENSE.rst
MANIFEST.in
README.rst
setup.cfg
setup.py
docs/index.rst
src/rc/__init__.py
src/rc.tiles.collection.egg-info/PKG-INFO
src/rc.tiles.collection.egg-info/SOURCES.txt
src/rc.tiles.collection.egg-info/dependency_links.txt
src/rc.tiles.collection.egg-info/entry_points.txt
src/rc.tiles.collection.egg-info/namespace_packages.txt
src/rc.tiles.collection.egg-info/not-zip-safe
src/rc.tiles.collection.egg-info/requires.txt
src/rc.tiles.collection.egg-info/top_level.txt
src/rc/tiles/__init__.py
src/rc/tiles/collection/.directory
src/rc/tiles/collection/__init__.py
src/rc/tiles/collection/collection.py
src/rc/tiles/collection/configure.zcml
src/rc/tiles/collection/interfaces.py
src/rc/tiles/collection/setuphandlers.py
src/rc/tiles/collection/testing.py
src/rc/tiles/collection/vocabularies.py
src/rc/tiles/collection/browser/__init__.py
src/rc/tiles/collection/browser/base_view.py
src/rc/tiles/collection/browser/configure.zcml
src/rc/tiles/collection/browser/custom_view.py
src/rc/tiles/collection/browser/custom_view2.py
src/rc/tiles/collection/browser/custom_view3.py
src/rc/tiles/collection/browser/overrides/.gitkeep
src/rc/tiles/collection/browser/static/.gitkeep
src/rc/tiles/collection/browser/static/tiles.css
src/rc/tiles/collection/browser/templates/base_view.pt
src/rc/tiles/collection/browser/templates/collection_tile.pt
src/rc/tiles/collection/browser/templates/custom_view.pt
src/rc/tiles/collection/browser/templates/custom_view2.pt
src/rc/tiles/collection/browser/templates/custom_view3.pt
src/rc/tiles/collection/locales/README.rst
src/rc/tiles/collection/locales/__init__.py
src/rc/tiles/collection/locales/rc.tiles.collection.pot
src/rc/tiles/collection/locales/update.py
src/rc/tiles/collection/locales/update.sh
src/rc/tiles/collection/locales/en/LC_MESSAGES/rc.tiles.collection.mo
src/rc/tiles/collection/locales/en/LC_MESSAGES/rc.tiles.collection.po
src/rc/tiles/collection/locales/it/LC_MESSAGES/collective.tiles.collection.mo
src/rc/tiles/collection/locales/it/LC_MESSAGES/collective.tiles.collection.po
src/rc/tiles/collection/profiles/default/browserlayer.xml
src/rc/tiles/collection/profiles/default/catalog.xml
src/rc/tiles/collection/profiles/default/metadata.xml
src/rc/tiles/collection/profiles/default/registry.xml
src/rc/tiles/collection/profiles/mosaic_support/registry.xml
