Metadata-Version: 1.1
Name: rc.tiles.collection
Version: 1.1.6
Summary: A tile that shows a set of collection results with a customizable layout
Home-page: https://pypi.python.org/pypi/rc.tiles.collection
Author: Rogerio da Costa
Author-email: rogeriocdluiz@gmail.com
License: GPL version 2
Keywords: Python Plone
Platform: UNKNOWN
Classifier: Environment :: Web Environment
Classifier: Framework :: Plone
Classifier: Framework :: Plone :: 5.0
Classifier: Framework :: Plone :: 5.1
Classifier: Programming Language :: Python
Classifier: Programming Language :: Python :: 2.7
Classifier: Operating System :: OS Independent
Classifier: License :: OSI Approved :: GNU General Public License v2 (GPLv2)
